mkdocs_code_validator/__init__.py
mkdocs_code_validator/plugin.py
mkdocs_code_validator/py.typed
mkdocs_code_validator-0.2.0.dist-info/METADATA
mkdocs_code_validator-0.2.0.dist-info/WHEEL
mkdocs_code_validator-0.2.0.dist-info/entry_points.txt
mkdocs_code_validator-0.2.0.dist-info/licenses/LICENSE.md
mkdocs_code_validator-0.2.0.dist-info/RECORD
