Metadata-Version: 2.1
Name: mkdocs-code-validator
Version: 0.2.0
Summary: Checks Markdown code blocks in a MkDocs site against user-defined actions
Project-URL: Documentation, https://oprypin.github.io/mkdocs-code-validator/
Project-URL: Source, https://github.com/oprypin/mkdocs-code-validator
Project-URL: Issues, https://github.com/oprypin/mkdocs-code-validator/issues
Author-email: Oleh Prypin <oleh@pryp.in>
License-Expression: MIT
License-File: LICENSE.md
Keywords: mkdocs,mkdocs-plugin
Classifier: Development Status :: 3 - Alpha
Classifier: Environment :: Console
Classifier: Environment :: Web Environment
Classifier: Intended Audience :: Developers
Classifier: License :: OSI Approved :: MIT License
Classifier: Operating System :: OS Independent
Classifier: Programming Language :: Python
Classifier: Programming Language :: Python :: 3.7
Classifier: Programming Language :: Python :: 3.8
Classifier: Programming Language :: Python :: 3.9
Classifier: Programming Language :: Python :: 3.10
Classifier: Programming Language :: Python :: 3.11
Classifier: Topic :: Documentation
Classifier: Topic :: Software Development :: Documentation
Classifier: Topic :: Text Processing :: Markup :: Markdown
Classifier: Typing :: Typed
Requires-Python: >=3.7
Requires-Dist: markdown>=3.3
Requires-Dist: mkdocs>=1.5.0
Requires-Dist: pymdown-extensions>=8.0
